{
  "$schema": "https://mintlify.com/docs.json",
  "name": "Consultoría Online",
  "theme": "almond",
  "colors": {
    "primary": "#2E86AB",
    "light": "#D9F0FA",
    "dark": "#1A5276"
  },
  "navbar": {
    "primary": {
      "type": "github",
      "href": "https://github.com/chaprot/ConsultoriaOnline"
    }
  },
  "footer": {
    "socials": {
      "github": "https://github.com/chaprot/ConsultoriaOnline"
    }
  },
  "navigation": {
    "tabs": [
      {
        "tab": "Documentation",
        "groups": [
          {
            "group": "Overview",
            "pages": ["introduction", "quickstart"]
          },
          {
            "group": "Core Features",
            "pages": [
              "features/user-registration",
              "features/questionnaire",
              "features/answer-types",
              "features/report-generation",
              "features/email-notifications"
            ]
          },
          {
            "group": "Architecture",
            "pages": [
              "architecture/overview",
              "architecture/data-model",
              "architecture/session-management"
            ]
          },
          {
            "group": "Configuration & Deployment",
            "pages": [
              "deployment/prerequisites",
              "deployment/database-setup",
              "deployment/web-config",
              "deployment/smtp-setup"
            ]
          }
        ]
      },
      {
        "tab": "Reference",
        "groups": [
          {
            "group": "Classes",
            "pages": [
              "reference/classes/pregunta",
              "reference/classes/respuesta-posible",
              "reference/classes/apartado-preguntas",
              "reference/classes/modelo-cuestionario"
            ]
          },
          {
            "group": "Data Access Layer",
            "pages": [
              "reference/dal/dal-pregunta",
              "reference/dal/dal-respuesta-del-usuario",
              "reference/dal/dal-usuario",
              "reference/dal/dal-respuesta-posible"
            ]
          },
          {
            "group": "FAQ",
            "pages": ["faq"]
          }
        ]
      }
    ]
  }
}
